<annotation>
	<folder>전처리1(동규)</folder>
	<filename>equlize_55_3131214.png</filename>
	<path>D:\project_dataset\전처리1(동규)\equlize_55_3131214.png</path>
	<source>
		<database>Unknown</database>
	</source>
	<size>
		<width>640</width>
		<height>640</height>
		<depth>3</depth>
	</size>
	<segmented>0</segmented>
	<object>
		<name>empty</name>
		<pose>Unspecified</pose>
		<truncated>0</truncated>
		<difficult>0</difficult>
		<bndbox>
			<xmin>145</xmin>
			<ymin>186</ymin>
			<xmax>305</xmax>
			<ymax>405</ymax>
		</bndbox>
	</object>
	<object>
		<name>empty</name>
		<pose>Unspecified</pose>
		<truncated>0</truncated>
		<difficult>0</difficult>
		<bndbox>
			<xmin>3</xmin>
			<ymin>195</ymin>
			<xmax>143</xmax>
			<ymax>404</ymax>
		</bndbox>
	</object>
	<object>
		<name>full</name>
		<pose>Unspecified</pose>
		<truncated>0</truncated>
		<difficult>0</difficult>
		<bndbox>
			<xmin>312</xmin>
			<ymin>184</ymin>
			<xmax>469</xmax>
			<ymax>446</ymax>
		</bndbox>
	</object>
</annotation>
