<annotation>
	<folder>전처리1(동규)</folder>
	<filename>equlize_52_6686639.png</filename>
	<path>D:\project_dataset\전처리1(동규)\equlize_52_6686639.png</path>
	<source>
		<database>Unknown</database>
	</source>
	<size>
		<width>640</width>
		<height>640</height>
		<depth>3</depth>
	</size>
	<segmented>0</segmented>
	<object>
		<name>empty</name>
		<pose>Unspecified</pose>
		<truncated>0</truncated>
		<difficult>0</difficult>
		<bndbox>
			<xmin>335</xmin>
			<ymin>144</ymin>
			<xmax>494</xmax>
			<ymax>459</ymax>
		</bndbox>
	</object>
	<object>
		<name>empty</name>
		<pose>Unspecified</pose>
		<truncated>0</truncated>
		<difficult>0</difficult>
		<bndbox>
			<xmin>512</xmin>
			<ymin>141</ymin>
			<xmax>637</xmax>
			<ymax>450</ymax>
		</bndbox>
	</object>
	<object>
		<name>full</name>
		<pose>Unspecified</pose>
		<truncated>0</truncated>
		<difficult>0</difficult>
		<bndbox>
			<xmin>159</xmin>
			<ymin>130</ymin>
			<xmax>331</xmax>
			<ymax>491</ymax>
		</bndbox>
	</object>
</annotation>
